pycdxml/__init__.py
pycdxml/cdxml_converter/__init__.py
pycdxml/cdxml_converter/cdx_objects.yml
pycdxml/cdxml_converter/cdx_properties.yml
pycdxml/cdxml_converter/charsets.yml
pycdxml/cdxml_converter/chemdraw_io.py
pycdxml/cdxml_converter/chemdraw_objects.py
pycdxml/cdxml_converter/chemdraw_types.py
pycdxml/cdxml_converter/rdkit_chemdraw.py
pycdxml/cdxml_slide_generator/ACS 1996.cdxml
pycdxml/cdxml_slide_generator/Angewandte.cdxml
pycdxml/cdxml_slide_generator/Comic.cdxml
pycdxml/cdxml_slide_generator/RSC.cdxml
pycdxml/cdxml_slide_generator/Wiley.cdxml
pycdxml/cdxml_slide_generator/__init__.py
pycdxml/cdxml_slide_generator/cdxml_slide_generator.py
pycdxml/cdxml_styler/__init__.py
pycdxml/cdxml_styler/cdxml_styler.py
pycdxml/cdxml_styler/styles.yml
pycdxml/utils/__init__.py
pycdxml/utils/cdxml_io.py
pycdxml/utils/font_handling.py
pycdxml/utils/geometry.py
pycdxml/utils/style.py
cdx_mol-0.0.4.dist-info/LICENSE.txt
cdx_mol-0.0.4.dist-info/METADATA
cdx_mol-0.0.4.dist-info/WHEEL
cdx_mol-0.0.4.dist-info/top_level.txt
cdx_mol-0.0.4.dist-info/RECORD
