Metadata-Version: 2.1
Name: cdx-mol
Version: 0.0.4
Summary: This is a file conversion library: cdx-mol
Requires-Python: >=3.6
License-File: LICENSE.txt
Requires-Dist: lxml (>=4.9.2)
